README.md
setup.py
pycassor/__init__.py
pycassor/__main__.py
pycassor.egg-info/PKG-INFO
pycassor.egg-info/SOURCES.txt
pycassor.egg-info/dependency_links.txt
pycassor.egg-info/entry_points.txt
pycassor.egg-info/not-zip-safe
pycassor.egg-info/requires.txt
pycassor.egg-info/top_level.txt