Metadata-Version: 2.1
Name: pycassor
Version: 0.0.1
Summary: Python Caviar Solutions Software suite
Home-page: https://github.com/dicaso/pycassor
Author: Christophe Van Neste
Author-email: christophe.vanneste@ugent.be
License: MIT
Platform: UNKNOWN
Requires-Python: >3.6
Provides-Extra: development
